{
    "parent": "minecraft:adventure/root",
    "criteria": {
        "dungeons_taverns:tavern_acacia": {
            "conditions": {
                "player": [
                    {
                        "condition": "minecraft:entity_properties",
                        "entity": "this",
                        "predicate": {
                            "location": {
                                "structure": "dungeons_taverns:tavern_acacia"
                            }
                        }
                    }
                ]
            },
            "trigger": "minecraft:location"
        },
        "dungeons_taverns:tavern_birch": {
            "conditions": {
                "player": [
                    {
                        "condition": "minecraft:entity_properties",
                        "entity": "this",
                        "predicate": {
                            "location": {
                                "structure": "dungeons_taverns:tavern_birch"
                            }
                        }
                    }
                ]
            },
            "trigger": "minecraft:location"
        },
        "dungeons_taverns:tavern_cherry": {
            "conditions": {
                "player": [
                    {
                        "condition": "minecraft:entity_properties",
                        "entity": "this",
                        "predicate": {
                            "location": {
                                "structure": "dungeons_taverns:tavern_cherry"
                            }
                        }
                    }
                ]
            },
            "trigger": "minecraft:location"
        },
        "dungeons_taverns:tavern_dark_oak": {
            "conditions": {
                "player": [
                    {
                        "condition": "minecraft:entity_properties",
                        "entity": "this",
                        "predicate": {
                            "location": {
                                "structure": "dungeons_taverns:tavern_dark_oak"
                            }
                        }
                    }
                ]
            },
            "trigger": "minecraft:location"
        },
        "dungeons_taverns:tavern_desert": {
            "conditions": {
                "player": [
                    {
                        "condition": "minecraft:entity_properties",
                        "entity": "this",
                        "predicate": {
                            "location": {
                                "structure": "dungeons_taverns:tavern_desert"
                            }
                        }
                    }
                ]
            },
            "trigger": "minecraft:location"
        },
        "dungeons_taverns:tavern_jungle": {
            "conditions": {
                "player": [
                    {
                        "condition": "minecraft:entity_properties",
                        "entity": "this",
                        "predicate": {
                            "location": {
                                "structure": "dungeons_taverns:tavern_jungle"
                            }
                        }
                    }
                ]
            },
            "trigger": "minecraft:location"
        },
        "dungeons_taverns:tavern_mangrove": {
            "conditions": {
                "player": [
                    {
                        "condition": "minecraft:entity_properties",
                        "entity": "this",
                        "predicate": {
                            "location": {
                                "structure": "dungeons_taverns:tavern_mangrove"
                            }
                        }
                    }
                ]
            },
            "trigger": "minecraft:location"
        },
        "dungeons_taverns:tavern_oak": {
            "conditions": {
                "player": [
                    {
                        "condition": "minecraft:entity_properties",
                        "entity": "this",
                        "predicate": {
                            "location": {
                                "structure": "dungeons_taverns:tavern_oak"
                            }
                        }
                    }
                ]
            },
            "trigger": "minecraft:location"
        },
        "dungeons_taverns:tavern_spruce": {
            "conditions": {
                "player": [
                    {
                        "condition": "minecraft:entity_properties",
                        "entity": "this",
                        "predicate": {
                            "location": {
                                "structure": "dungeons_taverns:tavern_spruce"
                            }
                        }
                    }
                ]
            },
            "trigger": "minecraft:location"
        },
        "dungeons_taverns:tavern_swamp": {
            "conditions": {
                "player": [
                    {
                        "condition": "minecraft:entity_properties",
                        "entity": "this",
                        "predicate": {
                            "location": {
                                "structure": "dungeons_taverns:tavern_swamp"
                            }
                        }
                    }
                ]
            },
            "trigger": "minecraft:location"
        },
        "dungeons_taverns:tavern_snowy": {
            "conditions": {
                "player": [
                    {
                        "condition": "minecraft:entity_properties",
                        "entity": "this",
                        "predicate": {
                            "location": {
                                "structure": "dungeons_taverns:tavern_snowy"
                            }
                        }
                    }
                ]
            },
            "trigger": "minecraft:location"
        }
    },
    "display": {
        "announce_to_chat": true,
        "description": {
            "translate": "Find a Tavern"
        },
        "frame": "task",
        "hidden": false,
        "icon": {
            "item": "minecraft:smoker"
        },
        "show_toast": true,
        "title": {
            "translate": "Safe Haven"
        }
    },
    "requirements": [
        [
            "dungeons_taverns:tavern_acacia",
            "dungeons_taverns:tavern_birch",
            "dungeons_taverns:tavern_cherry",
            "dungeons_taverns:tavern_dark_oak",
            "dungeons_taverns:tavern_desert",
            "dungeons_taverns:tavern_jungle",
            "dungeons_taverns:tavern_mangrove",
            "dungeons_taverns:tavern_oak",
            "dungeons_taverns:tavern_spruce",
            "dungeons_taverns:tavern_swamp",
			"dungeons_taverns:tavern_snowy"
        ]
    ],
    "sends_telemetry_event": false
}
